Metadata-Version: 2.1
Name: anutoolbox
Version: 0.0.4
Summary: Testing installation of Package
Home-page: https://github.com/mike-huls/toolbox_public
Author: Anusri M
Author-email: anusri.mukherjee20@gmail.com
License: MIT
Project-URL: Bug Tracker, https://github.com/mike-huls/toolbox_public/issues
Keywords: pypi,anutoolbox,tutorial
Platform: UNKNOWN
Classifier: Development Status :: 3 - Alpha
Classifier: Intended Audience :: Developers
Classifier: Topic :: Software Development :: Documentation
Classifier: License :: OSI Approved :: MIT License
Classifier: Programming Language :: Python :: 3
Classifier: Programming Language :: Python :: 3.7
Classifier: Programming Language :: Python :: 3.8
Classifier: Programming Language :: Python :: 3.9
License-File: LICENCE.txt
